spotijjjy/__init__.py
spotijjjy/abc_client.py
spotijjjy/handler.py
spotijjjy/main.py
spotijjjy/reddit.py
spotijjjy/song_service.py
spotijjjy/spotify_oauth_cache.py
spotijjjy/spotify_playlist_updater.py
spotijjjy-1.1.0.dist-info/LICENSE
spotijjjy-1.1.0.dist-info/METADATA
spotijjjy-1.1.0.dist-info/WHEEL
spotijjjy-1.1.0.dist-info/top_level.txt
spotijjjy-1.1.0.dist-info/RECORD
