Metadata-Version: 2.1
Name: spotijjjy
Version: 1.1.0
Summary: Generate Spotify playlists from a few REST services
Home-page: https://github.com/maxtara/Spotijjjy
Author: Max Tarasuik
Author-email: pip_public@tarasuik.com
License: UNKNOWN
Platform: UNKNOWN
Classifier: Programming Language :: Python :: 3
Classifier: License :: OSI Approved :: MIT License
Classifier: Operating System :: OS Independent
Requires-Python: >=3.6
Requires-Dist: spotipy
